inventree_rexel/__init__.py
inventree_rexel/core.py
inventree_rexel/datahandler.py
inventree_rexel/demo.py
inventree_rexel/helpers.py
inventree_rexel/serializers.py
inventree_rexel/version.py
inventree_rexel/views.py
inventree_rexel/static/RexelPanel.js
inventree_rexel_plugin-0.2.1.dist-info/LICENSE
inventree_rexel_plugin-0.2.1.dist-info/METADATA
inventree_rexel_plugin-0.2.1.dist-info/WHEEL
inventree_rexel_plugin-0.2.1.dist-info/entry_points.txt
inventree_rexel_plugin-0.2.1.dist-info/top_level.txt
inventree_rexel_plugin-0.2.1.dist-info/RECORD
