Metadata-Version: 2.1
Name: inventree-rexel-plugin
Version: 0.2.1
Summary: rexel product import plugin for InvenTree
Home-page: https://github.com/philipboy881/inventree-rexel-plugin
Author: Philip van der honing
Author-email: philipvanderhoning@gmail.com
License: MIT
Keywords: inventree rexel product import inventory
Requires-Python: >=3.9
License-File: LICENSE
Requires-Dist: tablib
Requires-Dist: requests
Requires-Dist: beautifulsoup4
Requires-Dist: python-dotenv
